Honeybadger_Extensions-0.1.2.dist-info/DESCRIPTION.rst
Honeybadger_Extensions-0.1.2.dist-info/METADATA
Honeybadger_Extensions-0.1.2.dist-info/RECORD
Honeybadger_Extensions-0.1.2.dist-info/WHEEL
Honeybadger_Extensions-0.1.2.dist-info/metadata.json
Honeybadger_Extensions-0.1.2.dist-info/top_level.txt
honeybadger_extensions/__init__.py
honeybadger_extensions/_helpers.py
honeybadger_extensions/base.py
honeybadger_extensions/celery.py
honeybadger_extensions/flask.py
