Metadata-Version: 2.0
Name: Honeybadger-Extensions
Version: 0.1.2
Summary: Honeybadger extension that can log exceptions raised by Flask or Celery, adding more context than the original  honeybadger python library.
Home-page: http://github.com/Workable/honeybadger-extensions
Author: Ioannis Foukarakis
Author-email: ioannis.foukarakis@gmail.com
License: MIT
Platform: any
Classifier: Environment :: Web Environment
Classifier: Intended Audience :: Developers
Classifier: License :: OSI Approved :: MIT License
Classifier: Operating System :: OS Independent
Classifier: Programming Language :: Python
Classifier: Programming Language :: Python :: 3
Classifier: Topic :: Software Development :: Libraries :: Python Modules
Requires-Dist: honeybadger (==0.1.2)
Requires-Dist: blinker (>=1.1)
Requires-Dist: Flask (>=0.8)
Requires-Dist: celery (~=4.1.0)
Provides-Extra: celery
Requires-Dist: celery (~=4.1.0); extra == 'celery'
Provides-Extra: test
Requires-Dist: nose; extra == 'test'
Requires-Dist: mock (==2.0.0); extra == 'test'
Requires-Dist: coverage (~=4.3.4); extra == 'test'
